MANIFEST.in
README.txt
setup.py
evasion/__init__.py
evasion/web/__init__.py
evasion/web/middleware.py
evasion/web/websetup.py
evasion/web/commonauth/__init__.py
evasion/web/commonauth/flatauth/__init__.py
evasion/web/commonauth/flatauth/plain.py
evasion/web/commonauth/flatauth/tests/__init__.py
evasion/web/commonauth/flatauth/tests/testflatauth.py
evasion/web/config/__init__.py
evasion/web/config/environment.py
evasion/web/config/middleware.py
evasion/web/config/repozewhomid.py
evasion/web/config/routing.py
evasion/web/controllers/__init__.py
evasion/web/controllers/error.py
evasion/web/controllers/root.py
evasion/web/lib/__init__.py
evasion/web/lib/app_globals.py
evasion/web/lib/authdetails.py
evasion/web/lib/base.py
evasion/web/lib/helpers.py
evasion/web/lib/modelmanager.py
evasion/web/model/__init__.py
evasion/web/public/__init__.py
evasion/web/public/css/__init__.py
evasion/web/scripts/__init__.py
evasion/web/scripts/main.py
evasion/web/scripts/ugp/__init__.py
evasion/web/templates/__init__.py
evasion/web/tests/__init__.py
evasion/web/tests/test_models.py
evasion/web/tests/functional/__init__.py
evasion_web.egg-info/PKG-INFO
evasion_web.egg-info/SOURCES.txt
evasion_web.egg-info/dependency_links.txt
evasion_web.egg-info/eager_resources.txt
evasion_web.egg-info/entry_points.txt
evasion_web.egg-info/namespace_packages.txt
evasion_web.egg-info/not-zip-safe
evasion_web.egg-info/paster_plugins.txt
evasion_web.egg-info/requires.txt
evasion_web.egg-info/top_level.txt
scripts/runweb