Metadata-Version: 1.0
Name: evasion-web
Version: 1.1.1
Summary: Pylons based web application framework on which the director admin is based.
Home-page: UNKNOWN
Author: Oisin Mulvihill
Author-email: oisinmulvihill at gmail dot com
License: UNKNOWN
Platform: UNKNOWN
